regelum/__init__.py
regelum/__internal/__init__.py
regelum/__internal/base.py
regelum/__internal/cues_fix.py
regelum/__internal/metadata.py
regelum/animation.py
regelum/callback.py
regelum/configure.py
regelum/constraint_parser.py
regelum/critic.py
regelum/data_buffers/__init__.py
regelum/data_buffers/batch_sampler.py
regelum/data_buffers/data_buffer.py
regelum/event.py
regelum/img/3wrobot.svg
regelum/img/cart.svg
regelum/img/default.svg
regelum/img/lunar_lander.svg
regelum/img/omnirobot.svg
regelum/img/pendulum.svg
regelum/model.py
regelum/objective.py
regelum/observer.py
regelum/optimizable/__init__.py
regelum/optimizable/core/__init__.py
regelum/optimizable/core/configs.py
regelum/optimizable/core/entities.py
regelum/optimizable/core/hooks.py
regelum/optimizable/optimizers.py
regelum/policy.py
regelum/predictor.py
regelum/scenario.py
regelum/simulator.py
regelum/stopping_criterion.py
regelum/system.py
regelum/typing.py
regelum/utils.py
regelum_control-0.3.3.dist-info/LICENSE
regelum_control-0.3.3.dist-info/METADATA
regelum_control-0.3.3.dist-info/WHEEL
regelum_control-0.3.3.dist-info/RECORD
