Metadata-Version: 2.1
Name: regelum-control
Version: 0.3.3
Summary: Regelum is a flexibly configurable framework for agent-environment simulation with a menu of predictive and reinforcement learning pipelines.
License: MIT
Author: Georgiy Malaniya
Author-email: pwlsd.gm@gmail.com> Anton Bolychev <bolychev.anton@gmail.com> Grigoriy Yaremenko <yaremenko8@gmail.com> Pavel Osinenko <p.osinenko@yandex.ru
Requires-Python: >=3.9,<4.0
Classifier: License :: OSI Approved :: MIT License
Classifier: Programming Language :: Python :: 3
Classifier: Programming Language :: Python :: 3.9
Classifier: Programming Language :: Python :: 3.10
Classifier: Programming Language :: Python :: 3.11
Classifier: Programming Language :: Python :: 3.12
Classifier: Programming Language :: Python :: 3.13
Requires-Dist: casadi (>=3.6.5,<4.0.0)
Requires-Dist: cues (>=0.3.0,<0.4.0)
Requires-Dist: dill (>=0.3.8,<0.4.0)
Requires-Dist: gitpython (>=3.1.42,<4.0.0)
Requires-Dist: matplotlib (>=3.7.1)
Requires-Dist: matplotx (>=0.3.8,<0.4.0)
Requires-Dist: mlflow (==2.4.1)
Requires-Dist: numpy (>=1.25.2)
Requires-Dist: omegaconf (>=2.3.0,<3.0.0)
Requires-Dist: pandas (>=1.5.3)
Requires-Dist: plotly (>=5.15.0)
Requires-Dist: pyqt5 (==5.15.10)
Requires-Dist: pyqt5-qt5 (>=5.15.2,<=5.15.13)
Requires-Dist: rehydra (==1.3.5)
Requires-Dist: rehydra-joblib-launcher (==1.3.0)
Requires-Dist: scipy (>=1.11.0)
Requires-Dist: svgpath2mpl (>=1.0.0,<2.0.0)
Requires-Dist: svgpathtools (>=1.6.1,<2.0.0)
Requires-Dist: tables (>=3.8.0)
Requires-Dist: torch (>=1.13.1)
